[
  {
    "id": "1",
    "authorId": 1,
    "title": "正方形 720x720",
    "slug": "zheng-fang-xing-720x720",
    "thumbnail": "2025/05/03/2bbf5996-db03-4ad6-adc2-45f2a49406da.jpg",
    "viewCount": 10,
    "likeCount": 2,
    "favoriteCount": 1,
    "commentCount": 3,
    "publishedAt": "2025-05-04T10:35:58.719Z",
    "updatedAt": "2025-05-05T11:27:48.984Z",
    "tags": [{ "id": "tag1", "name": "日记" }],
    "author": {
      "id": 1,
      "name": "梦梦",
      "avatar": "2025/05/03/14849228-a974-40ce-8878-17073f0111bf.jpg"
    },
    "width": 720,
    "height": 720
  },
  {
    "id": "2",
    "authorId": 1,
    "title": "横图 1280x720",
    "slug": "heng-tu-1280x720",
    "thumbnail": "2025/05/03/2bbf5996-db03-4ad6-adc2-45f2a49406da.jpg",
    "viewCount": 5,
    "likeCount": 1,
    "favoriteCount": 0,
    "commentCount": 1,
    "publishedAt": "2025-05-04T10:35:58.719Z",
    "updatedAt": "2025-05-05T11:27:48.984Z",
    "tags": [{ "id": "tag2", "name": "横图" }],
    "author": {
      "id": 1,
      "name": "梦梦",
      "avatar": "2025/05/03/14849228-a974-40ce-8878-17073f0111bf.jpg"
    },
    "width": 1280,
    "height": 720
  },
  {
    "id": "3",
    "authorId": 1,
    "title": "竖图 540x960",
    "slug": "shu-tu-540x960",
    "thumbnail": "2025/05/03/2bbf5996-db03-4ad6-adc2-45f2a49406da.jpg",
    "viewCount": 8,
    "likeCount": 0,
    "favoriteCount": 0,
    "commentCount": 0,
    "publishedAt": "2025-05-04T10:35:58.719Z",
    "updatedAt": "2025-05-05T11:27:48.984Z",
    "tags": [{ "id": "tag3", "name": "竖图" }],
    "author": {
      "id": 1,
      "name": "梦梦",
      "avatar": "2025/05/03/14849228-a974-40ce-8878-17073f0111bf.jpg"
    },
    "width": 540,
    "height": 960
  },
  {
    "id": "4",
    "authorId": 1,
    "title": "横图 1000x500",
    "slug": "heng-tu-1000x500",
    "thumbnail": "2025/05/03/2bbf5996-db03-4ad6-adc2-45f2a49406da.jpg",
    "viewCount": 12,
    "likeCount": 3,
    "favoriteCount": 2,
    "commentCount": 2,
    "publishedAt": "2025-05-04T10:35:58.719Z",
    "updatedAt": "2025-05-05T11:27:48.984Z",
    "tags": [{ "id": "tag4", "name": "横图" }],
    "author": {
      "id": 1,
      "name": "梦梦",
      "avatar": "2025/05/03/14849228-a974-40ce-8878-17073f0111bf.jpg"
    },
    "width": 1000,
    "height": 500
  },
  {
    "id": "5",
    "authorId": 1,
    "title": "竖图 500x1000",
    "slug": "shu-tu-500x1000",
    "thumbnail": "2025/05/03/2bbf5996-db03-4ad6-adc2-45f2a49406da.jpg",
    "viewCount": 7,
    "likeCount": 0,
    "favoriteCount": 0,
    "commentCount": 0,
    "publishedAt": "2025-05-04T10:35:58.719Z",
    "updatedAt": "2025-05-05T11:27:48.984Z",
    "tags": [{ "id": "tag5", "name": "竖图" }],
    "author": {
      "id": 1,
      "name": "梦梦",
      "avatar": "2025/05/03/14849228-a974-40ce-8878-17073f0111bf.jpg"
    },
    "width": 500,
    "height": 1000
  },
  {
    "id": "6",
    "authorId": 1,
    "title": "超高 500x2000",
    "slug": "chao-gao-500x2000",
    "thumbnail": "2025/05/03/2bbf5996-db03-4ad6-adc2-45f2a49406da.jpg",
    "viewCount": 4,
    "likeCount": 0,
    "favoriteCount": 0,
    "commentCount": 0,
    "publishedAt": "2025-05-04T10:35:58.719Z",
    "updatedAt": "2025-05-05T11:27:48.984Z",
    "tags": [{ "id": "tag6", "name": "超高" }],
    "author": {
      "id": 1,
      "name": "梦梦",
      "avatar": "2025/05/03/14849228-a974-40ce-8878-17073f0111bf.jpg"
    },
    "width": 500,
    "height": 2000
  },
  {
    "id": "7",
    "authorId": 1,
    "title": "超宽 2000x500",
    "slug": "chao-kuan-2000x500",
    "thumbnail": "2025/05/03/2bbf5996-db03-4ad6-adc2-45f2a49406da.jpg",
    "viewCount": 6,
    "likeCount": 1,
    "favoriteCount": 0,
    "commentCount": 0,
    "publishedAt": "2025-05-04T10:35:58.719Z",
    "updatedAt": "2025-05-05T11:27:48.984Z",
    "tags": [{ "id": "tag7", "name": "超宽" }],
    "author": {
      "id": 1,
      "name": "梦梦",
      "avatar": "2025/05/03/14849228-a974-40ce-8878-17073f0111bf.jpg"
    },
    "width": 2000,
    "height": 500
  },
  {
    "id": "8",
    "authorId": 1,
    "title": "自适应宽高自适应宽高自适应宽高自适应宽高自适应宽高自适应宽高自适应宽高自适应宽高自适应宽高",
    "slug": "zi-shi-ying-kuan-gao",
    "thumbnail": "2025/05/03/2bbf5996-db03-4ad6-adc2-45f2a49406da.jpg",
    "viewCount": 9,
    "likeCount": 2,
    "favoriteCount": 1,
    "commentCount": 1,
    "publishedAt": "2025-05-04T10:35:58.719Z",
    "updatedAt": "2025-05-05T11:27:48.984Z",
    "tags": [{ "id": "tag8", "name": "自适应" }],
    "author": {
      "id": 1,
      "name": "梦梦",
      "avatar": "2025/05/03/14849228-a974-40ce-8878-17073f0111bf.jpg"
    },
    "isLiked": true
  }
]
